opencvtools/__init__.py
opencvtools/capture.py
opencvtools/colors.py
opencvtools/fps_meter.py
opencvtools/img.py
opencvtools/video_preview.py
opencv_tools-0.2.1.dist-info/LICENSE
opencv_tools-0.2.1.dist-info/METADATA
opencv_tools-0.2.1.dist-info/WHEEL
opencv_tools-0.2.1.dist-info/top_level.txt
opencv_tools-0.2.1.dist-info/RECORD
