Metadata-Version: 2.1
Name: opencv-tools
Version: 0.2.1
Summary: Simple tools to help with opencv experimenting.
Home-page: https://github.com/wojtke/opencv-tools
Author: Wojciech Jasiński
Classifier: Programming Language :: Python :: 3
Classifier: Programming Language :: Python :: 3.6
Classifier: Programming Language :: Python :: 3.7
Classifier: Programming Language :: Python :: 3.8
Classifier: License :: OSI Approved :: MIT License
Requires-Python: >=3.6
License-File: LICENSE
Requires-Dist: opencv-python
